<?xml version="1.0" encoding="utf-8"?>
<Tests>
  <Test>
    <Id>0</Id>
    <TesterID>0000</TesterID>
    <TraineeID>1111</TraineeID>
    <Date>14/01/2019 09:00:00</Date>
    <TesterComment />
    <CarType>פרטי</CarType>
    <BeginAddress>
      <Address>
        <City></City>
        <Number></Number>
        <StreetName></StreetName>
      </Address>
    </BeginAddress>
    <Parameters>
      <Speed>False</Speed>
      <Distance>False</Distance>
      <ReversePark>False</ReversePark>
      <UsingVinkers>False</UsingVinkers>
      <UsingMirrors>False</UsingMirrors>
    </Parameters>
    <Passed>False</Passed>
  </Test>
</Tests>